score.sa.orm-0.4.0-py3.7-nspkg.pth
score/sa/orm/__init__.py
score/sa/orm/_init.py
score/sa/orm/_session.py
score/sa/orm/base.py
score/sa/orm/dataloader.py
score/sa/orm/helpers.py
score/sa/orm/triggers.py
score/sa/orm/views.py
score.sa.orm-0.4.0.dist-info/COPYING.LESSER.txt
score.sa.orm-0.4.0.dist-info/METADATA
score.sa.orm-0.4.0.dist-info/WHEEL
score.sa.orm-0.4.0.dist-info/namespace_packages.txt
score.sa.orm-0.4.0.dist-info/top_level.txt
score.sa.orm-0.4.0.dist-info/RECORD
